pycvs/__init__.py
pycvs/cli.py
pycvs/data.py
pycvs-0.0.3.data/scripts/pycvs
pycvs-0.0.3.dist-info/LICENSE
pycvs-0.0.3.dist-info/METADATA
pycvs-0.0.3.dist-info/WHEEL
pycvs-0.0.3.dist-info/top_level.txt
pycvs-0.0.3.dist-info/RECORD
