Metadata-Version: 2.1
Name: pycvs
Version: 0.0.3
Summary: A Python client for CVS projects
Home-page: https://github.com/gerson23/pycvs
Author: Gerson Carlos
Author-email: gerson.mtg@gmail.com
License: MIT
Platform: UNKNOWN
Classifier: Programming Language :: Python :: 3
Classifier: Programming Language :: Python :: 3.4
Classifier: Programming Language :: Python :: 3.5
Classifier: Programming Language :: Python :: 3.6
Classifier: Programming Language :: Python :: 3.7
Classifier: License :: OSI Approved :: MIT License
Classifier: Operating System :: Unix
Classifier: Topic :: Software Development :: Version Control :: CVS
Classifier: Topic :: Utilities
Requires-Dist: pexpect
Requires-Dist: colorama
